nomad/__init__.py
nomad/repo.py
nomad/utils.py
nomad/engine/__init__.py
nomad/engine/dbapi.py
nomad/engine/sqla.py
nomad-2.4.dist-info/LICENSE
nomad-2.4.dist-info/METADATA
nomad-2.4.dist-info/WHEEL
nomad-2.4.dist-info/entry_points.txt
nomad-2.4.dist-info/top_level.txt
nomad-2.4.dist-info/RECORD
