Metadata-Version: 2.1
Name: nomad
Version: 2.4
Summary: simple sql migration tool to save you from becoming mad
Author-email: Alexander Solovyov <alexander@solovyov.net>
License: ISC License
Project-URL: Homepage, http://github.com/piranha/nomad/
Classifier: Environment :: Console
Classifier: Intended Audience :: Developers
Classifier: License :: OSI Approved :: BSD License
Classifier: Operating System :: OS Independent
Classifier: Programming Language :: Python
Classifier: Topic :: Software Development
Classifier: Topic :: Software Development :: Version Control
Classifier: Topic :: Database
Requires-Python: >=3.2
License-File: LICENSE
Requires-Dist: opster ==5.0
Requires-Dist: termcolor ==2.2.0
Provides-Extra: test
Requires-Dist: SQLAlchemy ==1.4.52 ; extra == 'test'
Requires-Dist: prysk ==0.20.0 ; extra == 'test'
Requires-Dist: PyYAML ==6.0.1 ; extra == 'test'
Requires-Dist: jinja2 ==3.1.4 ; extra == 'test'
